LICENSE
README.md
setup.py
ozonzone.egg-info/PKG-INFO
ozonzone.egg-info/SOURCES.txt
ozonzone.egg-info/dependency_links.txt
ozonzone.egg-info/requires.txt
ozonzone.egg-info/top_level.txt
zone/OzonParser.py
zone/Parser.py
zone/Tracker.py
zone/__init__.py
zone/__main__.py
zone/exception.py